AUTHORS
HISTORY.rst
LICENSE
MANIFEST.in
README.rst
requirements.txt
setup.py
wakadump/__about__.py
wakadump/__init__.py
wakadump/cli.py
wakadump/compat.py
wakadump.egg-info/PKG-INFO
wakadump.egg-info/SOURCES.txt
wakadump.egg-info/dependency_links.txt
wakadump.egg-info/entry_points.txt
wakadump.egg-info/not-zip-safe
wakadump.egg-info/pbr.json
wakadump.egg-info/requires.txt
wakadump.egg-info/top_level.txt
wakadump/formats/__init__.py
wakadump/formats/csv.py
wakadump/formats/keenio.py