Metadata-Version: 2.1
Name: wakadump
Version: 5.0.0
Summary: Command line tool for converting WakaTime data dump files into various formats.
Home-page: https://github.com/wakatime/wakadump
Author: Alan Hamlett
Author-email: alan@wakatime.com
License: BSD
Platform: any
Classifier: Development Status :: 5 - Production/Stable
Classifier: Environment :: Console
Classifier: Intended Audience :: Developers
Classifier: License :: OSI Approved :: BSD License
Classifier: Natural Language :: English
Classifier: Programming Language :: Python :: 3
Classifier: Programming Language :: Python :: 3.6
Classifier: Programming Language :: Python :: 3.7
Classifier: Programming Language :: Python :: 3.8
Classifier: Programming Language :: Python :: 3.9
Classifier: Programming Language :: Python :: 3.10
Classifier: Topic :: Text Editors
License-File: LICENSE
License-File: AUTHORS
